simpleVideo
simpleImage
simpleAudio
